README.md
setup.py
src/elk.py
src/elk_stack.egg-info/PKG-INFO
src/elk_stack.egg-info/SOURCES.txt
src/elk_stack.egg-info/dependency_links.txt
src/elk_stack.egg-info/requires.txt
src/elk_stack.egg-info/top_level.txt