Metadata-Version: 2.1
Name: elk-stack
Version: 0.0.1
Summary: Complete ElasticSearch Stack
Home-page: https://github.com/AmirBahadorDev/elk-stack.git
Author: AmirBahadorDev
Author-email: amirbahadordev@gmail.com
License: UNKNOWN
Platform: UNKNOWN
Classifier: Programming Language :: Python :: 3
Classifier: Programming Language :: Python :: 3.6
Classifier: Programming Language :: Python :: 3.7
Classifier: Development Status :: 7 - Inactive
Classifier: License :: OSI Approved :: MIT License
Classifier: Operating System :: OS Independent
Provides-Extra: dev
